setup.py
act_as_executable/__init__.py
act_as_executable/example.py
act_as_executable.egg-info/PKG-INFO
act_as_executable.egg-info/SOURCES.txt
act_as_executable.egg-info/dependency_links.txt
act_as_executable.egg-info/requires.txt
act_as_executable.egg-info/top_level.txt