Metadata-Version: 1.1
Name: act-as-executable
Version: 1.0
Summary: A Python wrapper to build CLI wrappers
Home-page: UNKNOWN
Author: Jorge Niedbalski R.
Author-email: jnr@pyrosome.org
License: BSD
Keywords: cli-wrapper,cli,wrapper,wrap cli
Platform: UNKNOWN
Classifier: Intended Audience :: Developers
Classifier: Operating System :: Unix 
